xcloudClients/__init__.py
xcloudClients/xcloudClients.py
xcloudClients/resources/XCloudJDBC-2.10.6.7.jar
xcloudClients/resources/XCloudJDBC_SP_Procedure_Parser-0.1.3.jar
xcloudClients/resources/libthrift-0.9.2.jar
xcloudClients/resources/log4j-1.2.17.jar
xcloudClients/resources/lz4-1.3.0.jar
xcloudClients/resources/slf4j-api-1.7.5.jar
xcloudClients/resources/slf4j-log4j12-1.7.5.jar
xcloudClients/resources/slf4j-simple-1.7.5.jar
xcloudClients-0.4.0.dist-info/METADATA
xcloudClients-0.4.0.dist-info/WHEEL
xcloudClients-0.4.0.dist-info/top_level.txt
xcloudClients-0.4.0.dist-info/RECORD
