Metadata-Version: 2.1
Name: xcloudClients
Version: 0.4.0
Summary: 这是一个国信行云数据库并发查询python程序,主要应用于自动通报
Home-page: https://github.com/bailulue
Author: bailu
Author-email: yabailu@chinatelecom.cn
License: UNKNOWN
Platform: UNKNOWN
Requires-Dist: JPype1 (==1.5.0)
